clean_text/__init__.py
clean_text/main.py
simple_text_preprocessor-0.2.0.dist-info/METADATA
simple_text_preprocessor-0.2.0.dist-info/WHEEL
simple_text_preprocessor-0.2.0.dist-info/entry_points.txt
simple_text_preprocessor-0.2.0.dist-info/top_level.txt
simple_text_preprocessor-0.2.0.dist-info/RECORD
